MANIFEST.in
README.rst
setup.py
django_waitinglist.egg-info/PKG-INFO
django_waitinglist.egg-info/SOURCES.txt
django_waitinglist.egg-info/dependency_links.txt
django_waitinglist.egg-info/requires.txt
django_waitinglist.egg-info/top_level.txt
waitinglist/__init__.py
waitinglist/admin.py
waitinglist/forms.py
waitinglist/models.py
waitinglist/signals.py
waitinglist/stats.py
waitinglist/tests.py
waitinglist/trello.py
waitinglist/urls.py
waitinglist/views.py
waitinglist/management/__init__.py
waitinglist/management/commands/__init__.py
waitinglist/management/commands/export_to_trello.py
waitinglist/management/commands/mail_out_survey_links.py
waitinglist/management/commands/make_contact.py
waitinglist/templates/waitinglist/_list_signup.html
waitinglist/templates/waitinglist/_success.html
waitinglist/templates/waitinglist/email/initial_contact.txt
waitinglist/templates/waitinglist/email/initial_contact_subject.txt
waitinglist/templatetags/__init__.py
waitinglist/templatetags/waitinglist_tags.py