Metadata-Version: 1.1
Name: django-waitinglist
Version: 1.4.5
Summary: a Django waiting list app for running a private beta with cohorts support
Home-page: http://github.com/pinax/django-waitinglist
Author: Brian Rosner
Author-email: brosner@gmail.com
License: MIT
Platform: UNKNOWN
Classifier: Development Status :: 4 - Beta
Classifier: Environment :: Web Environment
Classifier: Intended Audience :: Developers
Classifier: License :: OSI Approved :: MIT License
Classifier: Operating System :: OS Independent
Classifier: Programming Language :: Python
Classifier: Framework :: Django
